[
    {
      "id": 0,
      "name": "Kotosław",
      "desc": "Opis kota",
      "age": 0,
      "image": "0.jpeg",
      "likedBy": [],
      "shelterId": 1
    },
    {
      "id": 1,
      "name": "Kotkinson",
      "desc": "Opis kota",
      "age": 1,
      "image": "1.jpeg",
      "likedBy": [],
      "shelterId": 1
    },
    {
      "id": 2,
      "name": "Kicia",
      "desc": "Opis kota",
      "age": 2,
      "image": "2.jpeg",
      "likedBy": [],
      "shelterId": 1
    },
    {
      "id": 3,
      "name": "Kocia",
      "desc": "Opis kota",
      "age": 3,
      "image": "3.jpeg",
      "likedBy": [],
      "shelterId": 1
    },
    {
      "id": 4,
      "name": "Kotek",
      "desc": "Opis kota",
      "age": 4,
      "image": "4.jpeg",
      "likedBy": [],
      "shelterId": 1
    },
    {
      "id": 5,
      "name": "KiciaKocia",
      "desc": "Opis kota",
      "age": 5,
      "image": "5.jpeg",
      "likedBy": [],
      "shelterId": 1
    },
    {
      "id": 6,
      "name": "Koteczek",
      "desc": "Opis kota",
      "age": 6,
      "image": "6.jpeg",
      "likedBy": [],
      "shelterId": 1
    },
    {
      "id": 7,
      "name": "Imie kota",
      "desc": "Opis kota",
      "age": 7,
      "image": "7.jpeg",
      "likedBy": [],
      "shelterId": 4
    },
    {
      "id": 8,
      "name": "Imie kota",
      "desc": "Opis kota",
      "age": 8,
      "image": "8.jpeg",
      "likedBy": [],
      "shelterId": 4
    },
    {
      "id": 9,
      "name": "Imie kota",
      "desc": "Opis kota",
      "age": 9,
      "image": "9.jpeg",
      "likedBy": [],
      "shelterId": 4
    },
    {
      "id": 10,
      "name": "Imie kota",
      "desc": "Opis kota",
      "age": 10,
      "image": "10.jpeg",
      "likedBy": [],
      "shelterId": 4
    },
    {
      "id": 11,
      "name": "Imie kota",
      "desc": "Opis kota",
      "age": 11,
      "image": "11.jpeg",
      "likedBy": [],
      "shelterId": 2
    },
    {
      "id": 12,
      "name": "Imie kota",
      "desc": "Opis kota",
      "age": 12,
      "image": "12.jpeg",
      "likedBy": [],
      "shelterId": 2
    },
    {
      "id": 13,
      "name": "Imie kota",
      "desc": "Opis kota",
      "age": 13,
      "image": "13.jpeg",
      "likedBy": [],
      "shelterId": 2
    },
    {
      "id": 14,
      "name": "Imie kota",
      "desc": "Opis kota",
      "age": 14,
      "image": "14.jpeg",
      "likedBy": [],
      "shelterId": 2
    },
    {
      "id": 15,
      "name": "Imie kota",
      "desc": "Opis kota",
      "age": 15,
      "image": "15.jpeg",
      "likedBy": [],
      "shelterId": 3
    },
    {
      "id": 16,
      "name": "Imie kota",
      "desc": "Opis kota",
      "age": 16,
      "image": "16.jpeg",
      "likedBy": [],
      "shelterId": 3
    },
    {
      "id": 17,
      "name": "Imie kota",
      "desc": "Opis kota",
      "age": 17,
      "image": "17.jpeg",
      "likedBy": [],
      "shelterId": 3
    },
    {
      "id": 18,
      "name": "Imie kota",
      "desc": "Opis kota",
      "age": 18,
      "image": "18.jpeg",
      "likedBy": [],
      "shelterId": 3
    }
  ]